datacleaners/__init__.py
datacleaners/cleaning.py
tests/__init__.py
tests/test_cleaning.py
datacleaners-0.5.0.dist-info/LICENSE
datacleaners-0.5.0.dist-info/METADATA
datacleaners-0.5.0.dist-info/WHEEL
datacleaners-0.5.0.dist-info/top_level.txt
datacleaners-0.5.0.dist-info/RECORD
