Metadata-Version: 2.1
Name: datacleaners
Version: 0.5.0
Summary: A package for cleaning data before machine learning.
Home-page: https://github.com/NageshMashette/dataCleaner
Author: Nagesh
Author-email: nageshmashette32@gmail.com
Classifier: Programming Language :: Python :: 3
Classifier: License :: OSI Approved :: MIT License
Classifier: Operating System :: OS Independent
Requires-Python: >=3.6
License-File: LICENSE
Requires-Dist: pandas
Requires-Dist: numpy
Requires-Dist: scikit-learn
